Metadata-Version: 1.2
Name: rulemanager
Version: 0.1.14
Summary: Manage Amazon CloudWatch rules via cli
Home-page: https://bitbucket.org/the_organization/rulemanager
Author: Blake Huber
Author-email: blakeca00@gmail.com
License: GPL-3.0
Keywords: Amazon AWS ec2 cloudwatch rules events
Platform: UNKNOWN
Classifier: Topic :: Software Development :: Build Tools
Classifier: Development Status :: 4 - Beta
Classifier: Programming Language :: Python :: 3.6
Classifier: Programming Language :: Python :: 3.7
Classifier: License :: OSI Approved :: GNU General Public License v3 (GPLv3)
Classifier: Operating System :: POSIX :: Linux
Requires-Python: >=3.6, <4
